setup.py
sky130_hdl21/__init__.py
sky130_hdl21/pdk_data.py
sky130_hdl21/pdk_logic.py
sky130_hdl21/test_netlists.py
sky130_hdl21/test_pdk.py
sky130_hdl21/test_site_sims.py
sky130_hdl21.egg-info/PKG-INFO
sky130_hdl21.egg-info/SOURCES.txt
sky130_hdl21.egg-info/dependency_links.txt
sky130_hdl21.egg-info/requires.txt
sky130_hdl21.egg-info/top_level.txt
sky130_hdl21/digital_cells/__init__.py
sky130_hdl21/digital_cells/high_density.py
sky130_hdl21/digital_cells/high_speed.py
sky130_hdl21/digital_cells/low_leakage.py
sky130_hdl21/digital_cells/low_power.py
sky130_hdl21/digital_cells/low_speed.py
sky130_hdl21/digital_cells/medium_speed.py
sky130_hdl21/primitives/__init__.py
sky130_hdl21/primitives/prim_dicts.py
sky130_hdl21/primitives/primitives.py