Metadata-Version: 2.1
Name: sky130-hdl21
Version: 5.0.0
Summary: SkyWater 130nm PDK Package for Hdl21
Home-page: https://github.com/dan-fritchman/Hdl21
Author: Dan Fritchman, Thomas Pluck
Requires-Python: >=3.7
Provides-Extra: dev
